setup.py
odoo/addons/base_rest_somconnexio/CHANGELOG.md
odoo/addons/base_rest_somconnexio/README.rst
odoo/addons/base_rest_somconnexio/__init__.py
odoo/addons/base_rest_somconnexio/__manifest__.py
odoo/addons/base_rest_somconnexio/controllers/__init__.py
odoo/addons/base_rest_somconnexio/controllers/controllers.py
odoo/addons/base_rest_somconnexio/demo/auth_api_key.xml
odoo/addons/base_rest_somconnexio/i18n/ca_ES.po
odoo/addons/base_rest_somconnexio/i18n/es.po
odoo/addons/base_rest_somconnexio/models/__init__.py
odoo/addons/base_rest_somconnexio/models/auth_api_key.py
odoo/addons/base_rest_somconnexio/services/__init__.py
odoo/addons/base_rest_somconnexio/services/ping_auth_api_service.py
odoo/addons/base_rest_somconnexio/services/ping_public_api_service.py
odoo/addons/base_rest_somconnexio/services/validator_helper.py
odoo/addons/base_rest_somconnexio/tests/__init__.py
odoo/addons/base_rest_somconnexio/tests/common_service.py
odoo/addons/base_rest_somconnexio/tests/services/__init__.py
odoo/addons/base_rest_somconnexio/tests/services/test_ping_auth_api_service.py
odoo/addons/base_rest_somconnexio/tests/services/test_ping_public_api_service.py
odoo_addon_base_rest_somconnexio.egg-info/PKG-INFO
odoo_addon_base_rest_somconnexio.egg-info/SOURCES.txt
odoo_addon_base_rest_somconnexio.egg-info/dependency_links.txt
odoo_addon_base_rest_somconnexio.egg-info/not-zip-safe
odoo_addon_base_rest_somconnexio.egg-info/requires.txt
odoo_addon_base_rest_somconnexio.egg-info/top_level.txt